aws/paramstore/__init__.py
aws/paramstore/paramstore.py
aws.paramstore-1.0.1.dist-info/METADATA
aws.paramstore-1.0.1.dist-info/WHEEL
aws.paramstore-1.0.1.dist-info/top_level.txt
aws.paramstore-1.0.1.dist-info/RECORD
